mattsollamatools/__init__.py
mattsollamatools/tools.py
mattsollamatools-0.0.25.dist-info/LICENSE.md
mattsollamatools-0.0.25.dist-info/METADATA
mattsollamatools-0.0.25.dist-info/WHEEL
mattsollamatools-0.0.25.dist-info/top_level.txt
mattsollamatools-0.0.25.dist-info/RECORD
