Metadata-Version: 2.1
Name: mattsollamatools
Version: 0.0.25
Summary: Tools for working with Ollama
Author-email: Matt Williams <m@technovangelist.com>
Project-URL: Homepage, https://technovangelist.com
Classifier: Programming Language :: Python :: 3
Classifier: Operating System :: OS Independent
Requires-Python: >=3.6
License-File: LICENSE.md
